matti/__init__.py
matti/matti.py
matti-0.1.0.dist-info/LICENSE
matti-0.1.0.dist-info/WHEEL
matti-0.1.0.dist-info/METADATA
matti-0.1.0.dist-info/RECORD
