Metadata-Version: 2.1
Name: matti
Version: 0.1.0
Summary: pattern match
Home-page: https://github.com/sh1ma/matti
Author: sh1ma
Author-email: in9lude@gmail.com
Requires-Python: >=3.8,<4.0
Classifier: Programming Language :: Python :: 3
Classifier: Programming Language :: Python :: 3.8
Requires-Dist: black (>=20.8b1,<21.0)
Project-URL: Repository, https://github.com/sh1ma/matti
